lippy/__init__.py
lippy/enums.py
lippy/exceptions.py
lippy/types.py
lippy/bnb/__init__.py
lippy/bnb/branch_and_bound.py
lippy/brute_force/__init__.py
lippy/brute_force/brute_force.py
lippy/dual/__init__.py
lippy/dual/dual_lp.py
lippy/game/__init__.py
lippy/game/zero_sum_game.py
lippy/gomory/__init__.py
lippy/gomory/cutting_plane_method.py
lippy/simplex/__init__.py
lippy/simplex/_simplex_table.py
lippy/simplex/simplex_method.py
lippy-0.0.5.dist-info/LICENSE
lippy-0.0.5.dist-info/METADATA
lippy-0.0.5.dist-info/WHEEL
lippy-0.0.5.dist-info/top_level.txt
lippy-0.0.5.dist-info/RECORD
